extfslib.py
extfslib-1.4.dist-info/LICENSE
extfslib-1.4.dist-info/METADATA
extfslib-1.4.dist-info/WHEEL
extfslib-1.4.dist-info/top_level.txt
extfslib-1.4.dist-info/RECORD
