Metadata-Version: 2.1
Name: extfslib
Version: 1.4
Summary: Midnight Commander extfslib helper library for writing extfs archive plugins.
Home-page: https://github.com/gryf/mc_extfslib
Author: Roman Dobosz
Author-email: gryf73@gmail.com
License: BSD 3-Clause License
Classifier: Development Status :: 5 - Production/Stable
Classifier: Environment :: Console
Classifier: Intended Audience :: Developers
Classifier: License :: OSI Approved :: BSD License
Classifier: Operating System :: OS Independent
Classifier: Programming Language :: Python
Classifier: Programming Language :: Python :: 3
Classifier: Programming Language :: Python :: 3.8
Classifier: Programming Language :: Python :: 3.9
Classifier: Programming Language :: Python :: 3.10
Classifier: Programming Language :: Python :: 3.11
Classifier: Topic :: Utilities
License-File: LICENSE
